[
  {
    "protocol": "vless",
    "location": "US",
    "ip": "162.159.12.210",
    "port": 443,
    "latency_ms": 93,
    "speed_mbps": 58.23,
    "name": "NodeHub 🇺🇸 >>::US"
  },
  {
    "protocol": "vless",
    "location": "未知",
    "ip": "104.21.47.19",
    "port": 443,
    "latency_ms": 95,
    "speed_mbps": 91.71,
    "name": "NodeHub VLESS-104"
  },
  {
    "protocol": "vless",
    "location": "US",
    "ip": "172.64.40.49",
    "port": 443,
    "latency_ms": 100,
    "speed_mbps": 55.39,
    "name": "NodeHub 🇺🇸 >>::US"
  },
  {
    "protocol": "vless",
    "location": "US",
    "ip": "172.64.145.202",
    "port": 443,
    "latency_ms": 112,
    "speed_mbps": 78.2,
    "name": "NodeHub 🇺🇸 >>::US"
  },
  {
    "protocol": "vless",
    "location": "未知",
    "ip": "199.232.78.120",
    "port": 443,
    "latency_ms": 260,
    "speed_mbps": 34.67,
    "name": "NodeHub VLESS-199"
  },
  {
    "protocol": "vless",
    "location": "未知",
    "ip": "172.64.32.75",
    "port": 443,
    "latency_ms": 272,
    "speed_mbps": 33.52,
    "name": "NodeHub VLESS-172"
  },
  {
    "protocol": "vless",
    "location": "FR",
    "ip": "104.18.45.137",
    "port": 443,
    "latency_ms": 294,
    "speed_mbps": 29.15,
    "name": "NodeHub 🇫🇷 >>::FR"
  },
  {
    "protocol": "vless",
    "location": "未知",
    "ip": "173.245.58.75",
    "port": 443,
    "latency_ms": 363,
    "speed_mbps": 27.79,
    "name": "NodeHub Channel"
  }
]